anemoi/plugins/bris/inference/apply_adiabatic_corrections/__init__.py
anemoi/plugins/bris/inference/apply_adiabatic_corrections/adiabatic_correct.py
anemoi/plugins/bris/inference/apply_adiabatic_corrections/adiabatic_correct_test.py
anemoi/plugins/bris/inference/apply_adiabatic_corrections/apply_adiabatic_corrections.py
anemoi/plugins/bris/inference/apply_adiabatic_corrections/apply_adiabatic_corrections_test.py
anemoi/plugins/bris/inference/apply_adiabatic_corrections/test_data.grib
anemoi/plugins/bris/inference/apply_adiabatic_corrections/test_data/1.grib
anemoi/plugins/bris/inference/apply_adiabatic_corrections/test_data/2.grib
bris_anemoi_plugins-0.1.2.dist-info/licenses/LICENSE
bris_anemoi_plugins-0.1.2.dist-info/METADATA
bris_anemoi_plugins-0.1.2.dist-info/WHEEL
bris_anemoi_plugins-0.1.2.dist-info/entry_points.txt
bris_anemoi_plugins-0.1.2.dist-info/top_level.txt
bris_anemoi_plugins-0.1.2.dist-info/RECORD
