Metadata-Version: 2.4
Name: bris-anemoi-plugins
Version: 0.1.2
Summary: Plugins needed for running the Bris model with Forecast-in-a-Box and anemoi-inference
License-Expression: Apache-2.0
Project-URL: Homepage, https://github.com/metno/bris-fiab
Project-URL: Issues, https://github.com/metno/bris-fiab/issues
Classifier: Programming Language :: Python :: 3
Classifier: Operating System :: OS Independent
Requires-Python: >=3.11
License-File: LICENSE
Requires-Dist: anemoi-inference>=0.8.1
Requires-Dist: metpy>=1.7.1
Requires-Dist: pint
Requires-Dist: earthkit-data
Dynamic: license-file
